Step3_StateMachines/FSM_MOORE/SIMPLE_TRAFFIC_LIGHT/clock_divider.vhd
library ieee;
use ieee.std_logic_1164.all;

entity clock_divider is
port(
    n_periods : in integer;
    clock_in  : in std_logic;
    clock_out : out std_logic
);
end entity clock_divider;

architecture Behavioral of clock_divider is
    signal r_clock_out : std_logic := '0';
    signal counter     : integer := 0;
begin

    clock_out <= r_clock_out;

    clk_div: process(clock_in)
    begin
        if rising_edge(clock_in) then
            if counter = n_periods-1 then
                counter <= 0;
                r_clock_out <= not r_clock_out;
            else
                counter <= counter +1;
            end if;
        end if;
    end process;

end architecture Behavioral;

Step3_StateMachines/FSM_MOORE/SIMPLE_TRAFFIC_LIGHT/traffic.vhd
library ieee;
use ieee.std_logic_1164.all;

entity traffic_lights is
    generic (
        delay_short : integer := 5;
        delay_long  : integer := 15
    );
    port (
        clk    : in STD_LOGIC;
        rst    : in STD_LOGIC;
        lights : out STD_LOGIC_VECTOR(5 downto  0)
    );
end entity traffic_lights;

architecture Behavioral of traffic_lights is
    type state_type is (s0, s1, s2, s3, s4, s5);
    signal state  : state_type := s1;
    signal counter: integer    := 0 ; 
begin




    traffic_fsm : process(clk, rst)
    begin
        if rst = '1' then
            state   <= s0;
            counter <= 0;
        --elsif rising_edge(clk) then
        else
            case state is
                when s0 =>
                    if counter < delay_long then
                        counter <= counter + 1 ;
                        state <= s0;
                    else
                        counter <= 0 ;
                        state <= s1;
                    end if;
                when s1 =>
                    if counter < delay_short then
                        counter <= counter + 1 ;
                        state <= s1;
                    else
                        counter <= 0 ;
                        state <= s2;
                    end if;
                when s2 =>
                    if counter < delay_short then
                        counter <= counter + 1 ;
                        state <= s2;
                    else
                        counter <= 0 ;
                        state <= s3;
                    end if;                
                when s3 =>
                    if counter < delay_long then
                        counter <= counter + 1 ;
                        state <= s3;
                    else
                        counter <= 0 ;
                        state <= s4;
                    end if;        
                when s4 =>
                    if counter < delay_short then
                        counter <= counter + 1 ;
                        state <= s4;
                    else
                        counter <= 0 ;
                        state <= s5;
                    end if;        
                when s5 =>
                    if counter < delay_short then
                        counter <= counter + 1 ;
                        state <= s5;
                    else
                        counter <= 0 ;
                        state <= s0;
                    end if;

                when others =>
                    state <= s0;  -- Added others case for completeness
                    counter <= 0;
            end case;
        end if;
    end process traffic_fsm;

    lights_process: process(state)
    begin
        case state is
            when s0 => lights <= "100001";
            when s1 => lights <= "010001";
            when s2 => lights <= "001001";
            when s3 => lights <= "001100";
            when s4 => lights <= "001010";
            when s5 => lights <= "001001";
            when others => lights <= "000000"; -- Default case
        end case;
    end process;

    -- _1sclk: entity work.clock_divider
    -- map port(
    --     n_periods => 5; -- For testing purposes we will generate a 200 ms clock
    --     clock_in  => clk;
    --     clock_out => clk_1s
    -- );

end architecture Behavioral;

Step3_StateMachines/FSM_MOORE/SIMPLE_TRAFFIC_LIGHT/traffic_top.vhd
library ieee;
use ieee.std_logic_1164.all;

entity traffic_top is
generic(
    periods_to_1sec : integer := 100000000
);
port(
    clk : in std_logic;
    rst : in std_logic;
    lights: out std_logic_vector(5 downto 0)
);
end entity traffic_top;



architecture Behavioral of traffic_top is
    signal clk_1s : std_logic := '0';
begin
    
    traffic : entity work.traffic_lights
    port map(
        clk => clk,
        rst => rst,
        lights => lights

    );

    clock1_s : entity work.clock_divider
    port map(
        n_periods => periods_to_1sec,
        clock_in  => clk,
        clock_out => clk_1s
    );

end architecture Behavioral;

Step3_StateMachines/FSM_MOORE/SIMPLE_TRAFFIC_LIGHT/tb_traffic.vhd
library ieee;
use ieee.std_logic_1164.all;
use std.env.all;

entity tb_traffic is
end entity tb_traffic;

architecture Behavioral of tb_traffic is
    signal clk : std_logic := '0';
    signal rst : std_logic := '0';
    signal lights : std_logic_vector(5 downto 0) := "000000";
    constant period : time := 100 ms;
begin

    gen_clk: process
    begin
        wait for period/2;
        clk <= not clk;
    end process;


    UUT: entity work.traffic_top
    generic map(
      periods_to_1sec => 10  
    )
    port map(
        clk => clk,
        rst => rst,
        lights => lights
    );


    stimulii: process
    begin
        wait for 200000 ms;
        std.env.finish;
    end process;

end architecture Behavioral;

Step3_StateMachines/FSM_MOORE/SIMPLE_TRAFFIC_LIGHT/waveform_traffic.vcd
$date
   Fri Sep  5 14:25:26 2025
$end

$version
  2023.2
$end

$timescale
  1ps
$end

$scope module tb_traffic $end
$var wire 1 ! clk $end
$var wire 1 " rst $end
$var wire 6 # lights $end
$scope module UUT $end
$var wire 1 ! clk $end
$var wire 1 " rst $end
$var wire 6 # lights $end
$var wire 1 $ clk_1s $end
$scope module traffic $end
$var wire 1 ! clk $end
$var wire 1 " rst $end
$var wire 6 # lights $end
$upscope $end
$scope module clock1_s $end
$var wire 1 ! clock_in $end
$var wire 1 $ clock_out $end
$var wire 1 % r_clock_out $end
$upscope $end
$upscope $end
$upscope $end
$enddefinitions $end

#0
$dumpvars
0!
0"
b10001 #
0$
0%
$end

#50000000000
1!

#100000000000
0!

#150000000000
1!

#200000000000
0!

#250000000000
1!
b1001 #

#300000000000
0!

#350000000000
1!

#400000000000
0!

#450000000000
1!

#500000000000
0!

#550000000000
1!
b1100 #

#600000000000
0!

#650000000000
1!

#700000000000
0!

#750000000000
1!

#800000000000
0!

#850000000000
1!

#900000000000
0!

#950000000000
1!
1$
1%

#1000000000000
0!

#1050000000000
1!

#1100000000000
0!

#1150000000000
1!

#1200000000000
0!

#1250000000000
1!

#1300000000000
0!

#1350000000000
1!
b1010 #

#1400000000000
0!

#1450000000000
1!

#1500000000000
0!

#1550000000000
1!

#1600000000000
0!

#1650000000000
1!
b1001 #

#1700000000000
0!

#1750000000000
1!

#1800000000000
0!

#1850000000000
1!

#1900000000000
0!

#1950000000000
1!
b100001 #
0$
0%

#2000000000000
0!

#2050000000000
1!

#2100000000000
0!

#2150000000000
1!

#2200000000000
0!

#2250000000000
1!

#2300000000000
0!

#2350000000000
1!

#2400000000000
0!

#2450000000000
1!

#2500000000000
0!

#2550000000000
1!

#2600000000000
0!

#2650000000000
1!

#2700000000000
0!

#2750000000000
1!
b10001 #

#2800000000000
0!

#2850000000000
1!

#2900000000000
0!

#2950000000000
1!
1$
1%

#3000000000000
0!

#3050000000000
1!
b1001 #

#3100000000000
0!

#3150000000000
1!

#3200000000000
0!

#3250000000000
1!

#3300000000000
0!

#3350000000000
1!
b1100 #

#3400000000000
0!

#3450000000000
1!

#3500000000000
0!

#3550000000000
1!

#3600000000000
0!

#3650000000000
1!

#3700000000000
0!

#3750000000000
1!

#3800000000000
0!

#3850000000000
1!

#3900000000000
0!

#3950000000000
1!
0$
0%

#4000000000000
0!

#4050000000000
1!

#4100000000000
0!

#4150000000000
1!
b1010 #

#4200000000000
0!

#4250000000000
1!

#4300000000000
0!

#4350000000000
1!

#4400000000000
0!

#4450000000000
1!
b1001 #

#4500000000000
0!

#4550000000000
1!

#4600000000000
0!

#4650000000000
1!

#4700000000000
0!

#4750000000000
1!
b100001 #

#4800000000000
0!

#4850000000000
1!

#4900000000000
0!

#4950000000000
1!
1$
1%

#5000000000000
0!

#5050000000000
1!

#5100000000000
0!

#5150000000000
1!

#5200000000000
0!

#5250000000000
1!

#5300000000000
0!

#5350000000000
1!

#5400000000000
0!

#5450000000000
1!

#5500000000000
0!

#5550000000000
1!
b10001 #

#5600000000000
0!

#5650000000000
1!

#5700000000000
0!

#5750000000000
1!

#5800000000000
0!

#5850000000000
1!
b1001 #

#5900000000000
0!

#5950000000000
1!
0$
0%

#6000000000000
0!

#6050000000000
1!

#6100000000000
0!

#6150000000000
1!
b1100 #

#6200000000000
0!

#6250000000000
1!

#6300000000000
0!

#6350000000000
1!

#6400000000000
0!

#6450000000000
1!

#6500000000000
0!

#6550000000000
1!

#6600000000000
0!

#6650000000000
1!

#6700000000000
0!

#6750000000000
1!

#6800000000000
0!

#6850000000000
1!

#6900000000000
0!

#6950000000000
1!
b1010 #
1$
1%

#7000000000000
0!

#7050000000000
1!

#7100000000000
0!

#7150000000000
1!

#7200000000000
0!

#7250000000000
1!
b1001 #

#7300000000000
0!

#7350000000000
1!

#7400000000000
0!

#7450000000000
1!

#7500000000000
0!

#7550000000000
1!
b100001 #

#7600000000000
0!

#7650000000000
1!

#7700000000000
0!

#7750000000000
1!

#7800000000000
0!

#7850000000000
1!

#7900000000000
0!

#7950000000000
1!
0$
0%

#8000000000000
0!

#8050000000000
1!

#8100000000000
0!

#8150000000000
1!

#8200000000000
0!

#8250000000000
1!

#8300000000000
0!

#8350000000000
1!
b10001 #

#8400000000000
0!

#8450000000000
1!

#8500000000000
0!

#8550000000000
1!

#8600000000000
0!

#8650000000000
1!
b1001 #

#8700000000000
0!

#8750000000000
1!

#8800000000000
0!

#8850000000000
1!

#8900000000000
0!

#8950000000000
1!
b1100 #
1$
1%

#9000000000000
0!

#9050000000000
1!

#9100000000000
0!

#9150000000000
1!

#9200000000000
0!

#9250000000000
1!

#9300000000000
0!

#9350000000000
1!

#9400000000000
0!

#9450000000000
1!

#9500000000000
0!

#9550000000000
1!

#9600000000000
0!

#9650000000000
1!

#9700000000000
0!

#9750000000000
1!
b1010 #

#9800000000000
0!

#9850000000000
1!

#9900000000000
0!

#9950000000000
1!
0$
0%

#10000000000000
0!

#10050000000000
1!
b1001 #

#10100000000000
0!

#10150000000000
1!

#10200000000000
0!

#10250000000000
1!

#10300000000000
0!

#10350000000000
1!
b100001 #

#10400000000000
0!

#10450000000000
1!

#10500000000000
0!

#10550000000000
1!

#10600000000000
0!

#10650000000000
1!

#10700000000000
0!

#10750000000000
1!

#10800000000000
0!

#10850000000000
1!

#10900000000000
0!

#10950000000000
1!
1$
1%

#11000000000000
0!

#11050000000000
1!

#11100000000000
0!

#11150000000000
1!
b10001 #

#11200000000000
0!

#11250000000000
1!

#11300000000000
0!

#11350000000000
1!

#11400000000000
0!

#11450000000000
1!
b1001 #

#11500000000000
0!

#11550000000000
1!

#11600000000000
0!

#11650000000000
1!

#11700000000000
0!

#11750000000000
1!
b1100 #

#11800000000000
0!

#11850000000000
1!

#11900000000000
0!

#11950000000000
1!
0$
0%

#12000000000000
0!

#12050000000000
1!

#12100000000000
0!

#12150000000000
1!

#12200000000000
0!

#12250000000000
1!

#12300000000000
0!

#12350000000000
1!

#12400000000000
0!

#12450000000000
1!

#12500000000000
0!

#12550000000000
1!
b1010 #

#12600000000000
0!

#12650000000000
1!

#12700000000000
0!

#12750000000000
1!

#12800000000000
0!

#12850000000000
1!
b1001 #

#12900000000000
0!

#12950000000000
1!
1$
1%

#13000000000000
0!

#13050000000000
1!

#13100000000000
0!

#13150000000000
1!
b100001 #

#13200000000000
0!

#13250000000000
1!

#13300000000000
0!

#13350000000000
1!

#13400000000000
0!

#13450000000000
1!

#13500000000000
0!

#13550000000000
1!

#13600000000000
0!

#13650000000000
1!

#13700000000000
0!

#13750000000000
1!

#13800000000000
0!

#13850000000000
1!

#13900000000000
0!

#13950000000000
1!
b10001 #
0$
0%

#14000000000000
0!

#14050000000000
1!

#14100000000000
0!

#14150000000000
1!

#14200000000000
0!

#14250000000000
1!
b1001 #

#14300000000000
0!

#14350000000000
1!

#14400000000000
0!

#14450000000000
1!

#14500000000000
0!

#14550000000000
1!
b1100 #

#14600000000000
0!

#14650000000000
1!

#14700000000000
0!

#14750000000000
1!

#14800000000000
0!

#14850000000000
1!

#14900000000000
0!

#14950000000000
1!
1$
1%

#15000000000000
0!

#15050000000000
1!

#15100000000000
0!

#15150000000000
1!

#15200000000000
0!

#15250000000000
1!

#15300000000000
0!

#15350000000000
1!
b1010 #

#15400000000000
0!

#15450000000000
1!

#15500000000000
0!

#15550000000000
1!

#15600000000000
0!

#15650000000000
1!
b1001 #

#15700000000000
0!

#15750000000000
1!

#15800000000000
0!

#15850000000000
1!

#15900000000000
0!

#15950000000000
1!
b100001 #
0$
0%

#16000000000000
0!

#16050000000000
1!

#16100000000000
0!

#16150000000000
1!

#16200000000000
0!

#16250000000000
1!

#16300000000000
0!

#16350000000000
1!

#16400000000000
0!

#16450000000000
1!

#16500000000000
0!

#16550000000000
1!

#16600000000000
0!

#16650000000000
1!

#16700000000000
0!

#16750000000000
1!
b10001 #

#16800000000000
0!

#16850000000000
1!

#16900000000000
0!

#16950000000000
1!
1$
1%

#17000000000000
0!

#17050000000000
1!
b1001 #

#17100000000000
0!

#17150000000000
1!

#17200000000000
0!

#17250000000000
1!

#17300000000000
0!

#17350000000000
1!
b1100 #

#17400000000000
0!

#17450000000000
1!

#17500000000000
0!

#17550000000000
1!

#17600000000000
0!

#17650000000000
1!

#17700000000000
0!

#17750000000000
1!

#17800000000000
0!

#17850000000000
1!

#17900000000000
0!

#17950000000000
1!
0$
0%

#18000000000000
0!

#18050000000000
1!

#18100000000000
0!

#18150000000000
1!
b1010 #

#18200000000000
0!

#18250000000000
1!

#18300000000000
0!

#18350000000000
1!

#18400000000000
0!

#18450000000000
1!
b1001 #

#18500000000000
0!

#18550000000000
1!

#18600000000000
0!

#18650000000000
1!

#18700000000000
0!

#18750000000000
1!
b100001 #

#18800000000000
0!

#18850000000000
1!

#18900000000000
0!

#18950000000000
1!
1$
1%

#19000000000000
0!

#19050000000000
1!

#19100000000000
0!

#19150000000000
1!

#19200000000000
0!

#19250000000000
1!

#19300000000000
0!

#19350000000000
1!

#19400000000000
0!

#19450000000000
1!

#19500000000000
0!

#19550000000000
1!
b10001 #

#19600000000000
0!

#19650000000000
1!

#19700000000000
0!

#19750000000000
1!

#19800000000000
0!

#19850000000000
1!
b1001 #

#19900000000000
0!

#19950000000000
1!
0$
0%

#20000000000000
0!

#20050000000000
1!

#20100000000000
0!

#20150000000000
1!
b1100 #

#20200000000000
0!

#20250000000000
1!

#20300000000000
0!

#20350000000000
1!

#20400000000000
0!

#20450000000000
1!

#20500000000000
0!

#20550000000000
1!

#20600000000000
0!

#20650000000000
1!

#20700000000000
0!

#20750000000000
1!

#20800000000000
0!

#20850000000000
1!

#20900000000000
0!

#20950000000000
1!
b1010 #
1$
1%

#21000000000000
0!

#21050000000000
1!

#21100000000000
0!

#21150000000000
1!

#21200000000000
0!

#21250000000000
1!
b1001 #

#21300000000000
0!

#21350000000000
1!

#21400000000000
0!

#21450000000000
1!

#21500000000000
0!

#21550000000000
1!
b100001 #

#21600000000000
0!

#21650000000000
1!

#21700000000000
0!

#21750000000000
1!

#21800000000000
0!

#21850000000000
1!

#21900000000000
0!

#21950000000000
1!
0$
0%

#22000000000000
0!

#22050000000000
1!

#22100000000000
0!

#22150000000000
1!

#22200000000000
0!

#22250000000000
1!

#22300000000000
0!

#22350000000000
1!
b10001 #

#22400000000000
0!

#22450000000000
1!

#22500000000000
0!

#22550000000000
1!

#22600000000000
0!

#22650000000000
1!
b1001 #

#22700000000000
0!

#22750000000000
1!

#22800000000000
0!

#22850000000000
1!

#22900000000000
0!

#22950000000000
1!
b1100 #
1$
1%

#23000000000000
0!

#23050000000000
1!

#23100000000000
0!

#23150000000000
1!

#23200000000000
0!

#23250000000000
1!

#23300000000000
0!

#23350000000000
1!

#23400000000000
0!

#23450000000000
1!

#23500000000000
0!

#23550000000000
1!

#23600000000000
0!

#23650000000000
1!

#23700000000000
0!

#23750000000000
1!
b1010 #

#23800000000000
0!

#23850000000000
1!

#23900000000000
0!

#23950000000000
1!
0$
0%

#24000000000000
0!

#24050000000000
1!
b1001 #

#24100000000000
0!

#24150000000000
1!

#24200000000000
0!

#24250000000000
1!

#24300000000000
0!

#24350000000000
1!
b100001 #

#24400000000000
0!

#24450000000000
1!

#24500000000000
0!

#24550000000000
1!

#24600000000000
0!

#24650000000000
1!

#24700000000000
0!

#24750000000000
1!

#24800000000000
0!

#24850000000000
1!

#24900000000000
0!

#24950000000000
1!
1$
1%

#25000000000000
0!

#25050000000000
1!

#25100000000000
0!

#25150000000000
1!
b10001 #

#25200000000000
0!

#25250000000000
1!

#25300000000000
0!

#25350000000000
1!

#25400000000000
0!

#25450000000000
1!
b1001 #

#25500000000000
0!

#25550000000000
1!

#25600000000000
0!

#25650000000000
1!

#25700000000000
0!

#25750000000000
1!
b1100 #

#25800000000000
0!

#25850000000000
1!

#25900000000000
0!

#25950000000000
1!
0$
0%

#26000000000000
0!

#26050000000000
1!

#26100000000000
0!

#26150000000000
1!

#26200000000000
0!

#26250000000000
1!

#26300000000000
0!

#26350000000000
1!

#26400000000000
0!

#26450000000000
1!

#26500000000000
0!

#26550000000000
1!
b1010 #

#26600000000000
0!

#26650000000000
1!

#26700000000000
0!

#26750000000000
1!

#26800000000000
0!

#26850000000000
1!
b1001 #

#26900000000000
0!

#26950000000000
1!
1$
1%

#27000000000000
0!

#27050000000000
1!

#27100000000000
0!

#27150000000000
1!
b100001 #

#27200000000000
0!

#27250000000000
1!

#27300000000000
0!

#27350000000000
1!

#27400000000000
0!

#27450000000000
1!

#27500000000000
0!

#27550000000000
1!

#27600000000000
0!

#27650000000000
1!

#27700000000000
0!

#27750000000000
1!

#27800000000000
0!

#27850000000000
1!

#27900000000000
0!

#27950000000000
1!
b10001 #
0$
0%

#28000000000000
0!

#28050000000000
1!

#28100000000000
0!

#28150000000000
1!

#28200000000000
0!

#28250000000000
1!
b1001 #

#28300000000000
0!

#28350000000000
1!

#28400000000000
0!

#28450000000000
1!

#28500000000000
0!

#28550000000000
1!
b1100 #

#28600000000000
0!

#28650000000000
1!

#28700000000000
0!

#28750000000000
1!

#28800000000000
0!

#28850000000000
1!

#28900000000000
0!

#28950000000000
1!
1$
1%

#29000000000000
0!

#29050000000000
1!

#29100000000000
0!

#29150000000000
1!

#29200000000000
0!

#29250000000000
1!

#29300000000000
0!

#29350000000000
1!
b1010 #

#29400000000000
0!

#29450000000000
1!

#29500000000000
0!

#29550000000000
1!

#29600000000000
0!

#29650000000000
1!
b1001 #

#29700000000000
0!

#29750000000000
1!

#29800000000000
0!

#29850000000000
1!

#29900000000000
0!

#29950000000000
1!
b100001 #
0$
0%

#30000000000000
0!

#30050000000000
1!

#30100000000000
0!

#30150000000000
1!

#30200000000000
0!

#30250000000000
1!

#30300000000000
0!

#30350000000000
1!

#30400000000000
0!

#30450000000000
1!

#30500000000000
0!

#30550000000000
1!

#30600000000000
0!

#30650000000000
1!

#30700000000000
0!

#30750000000000
1!
b10001 #

#30800000000000
0!

#30850000000000
1!

#30900000000000
0!

#30950000000000
1!
1$
1%

#31000000000000
0!

#31050000000000
1!
b1001 #

#31100000000000
0!

#31150000000000
1!

#31200000000000
0!

#31250000000000
1!

#31300000000000
0!

#31350000000000
1!
b1100 #

#31400000000000
0!

#31450000000000
1!

#31500000000000
0!

#31550000000000
1!

#31600000000000
0!

#31650000000000
1!

#31700000000000
0!

#31750000000000
1!

#31800000000000
0!

#31850000000000
1!

#31900000000000
0!

#31950000000000
1!
0$
0%

#32000000000000
0!

#32050000000000
1!

#32100000000000
0!

#32150000000000
1!
b1010 #

#32200000000000
0!

#32250000000000
1!

#32300000000000
0!

#32350000000000
1!

#32400000000000
0!

#32450000000000
1!
b1001 #

#32500000000000
0!

#32550000000000
1!

#32600000000000
0!

#32650000000000
1!

#32700000000000
0!

#32750000000000
1!
b100001 #

#32800000000000
0!

#32850000000000
1!

#32900000000000
0!

#32950000000000
1!
1$
1%

#33000000000000
0!

#33050000000000
1!

#33100000000000
0!

#33150000000000
1!

#33200000000000
0!

#33250000000000
1!

#33300000000000
0!

#33350000000000
1!

#33400000000000
0!

#33450000000000
1!

#33500000000000
0!

#33550000000000
1!
b10001 #

#33600000000000
0!

#33650000000000
1!

#33700000000000
0!

#33750000000000
1!

#33800000000000
0!

#33850000000000
1!
b1001 #

#33900000000000
0!

#33950000000000
1!
0$
0%

#34000000000000
0!

#34050000000000
1!

#34100000000000
0!

#34150000000000
1!
b1100 #

#34200000000000
0!

#34250000000000
1!

#34300000000000
0!

#34350000000000
1!

#34400000000000
0!

#34450000000000
1!

#34500000000000
0!

#34550000000000
1!

#34600000000000
0!

#34650000000000
1!

#34700000000000
0!

#34750000000000
1!

#34800000000000
0!

#34850000000000
1!

#34900000000000
0!

#34950000000000
1!
b1010 #
1$
1%

#35000000000000
0!

#35050000000000
1!

#35100000000000
0!

#35150000000000
1!

#35200000000000
0!

#35250000000000
1!
b1001 #

#35300000000000
0!

#35350000000000
1!

#35400000000000
0!

#35450000000000
1!

#35500000000000
0!

#35550000000000
1!
b100001 #

#35600000000000
0!

#35650000000000
1!

#35700000000000
0!

#35750000000000
1!

#35800000000000
0!

#35850000000000
1!

#35900000000000
0!

#35950000000000
1!
0$
0%

#36000000000000
0!

#36050000000000
1!

#36100000000000
0!

#36150000000000
1!

#36200000000000
0!

#36250000000000
1!

#36300000000000
0!

#36350000000000
1!
b10001 #

#36400000000000
0!

#36450000000000
1!

#36500000000000
0!

#36550000000000
1!

#36600000000000
0!

#36650000000000
1!
b1001 #

#36700000000000
0!

#36750000000000
1!

#36800000000000
0!

#36850000000000
1!

#36900000000000
0!

#36950000000000
1!
b1100 #
1$
1%

#37000000000000
0!

#37050000000000
1!

#37100000000000
0!

#37150000000000
1!

#37200000000000
0!

#37250000000000
1!

#37300000000000
0!

#37350000000000
1!

#37400000000000
0!

#37450000000000
1!

#37500000000000
0!

#37550000000000
1!

#37600000000000
0!

#37650000000000
1!

#37700000000000
0!

#37750000000000
1!
b1010 #

#37800000000000
0!

#37850000000000
1!

#37900000000000
0!

#37950000000000
1!
0$
0%

#38000000000000
0!

#38050000000000
1!
b1001 #

#38100000000000
0!

#38150000000000
1!

#38200000000000
0!

#38250000000000
1!

#38300000000000
0!

#38350000000000
1!
b100001 #

#38400000000000
0!

#38450000000000
1!

#38500000000000
0!

#38550000000000
1!

#38600000000000
0!

#38650000000000
1!

#38700000000000
0!

#38750000000000
1!

#38800000000000
0!

#38850000000000
1!

#38900000000000
0!

#38950000000000
1!
1$
1%

#39000000000000
0!

#39050000000000
1!

#39100000000000
0!

#39150000000000
1!
b10001 #

#39200000000000
0!

#39250000000000
1!

#39300000000000
0!

#39350000000000
1!

#39400000000000
0!

#39450000000000
1!
b1001 #

#39500000000000
0!

#39550000000000
1!

#39600000000000
0!

#39650000000000
1!

#39700000000000
0!

#39750000000000
1!
b1100 #

#39800000000000
0!

#39850000000000
1!

#39900000000000
0!

#39950000000000
1!
0$
0%

#40000000000000
0!

#40050000000000
1!

#40100000000000
0!

#40150000000000
1!

#40200000000000
0!

#40250000000000
1!

#40300000000000
0!

#40350000000000
1!

#40400000000000
0!

#40450000000000
1!

#40500000000000
0!

#40550000000000
1!
b1010 #

#40600000000000
0!

#40650000000000
1!

#40700000000000
0!

#40750000000000
1!

#40800000000000
0!

#40850000000000
1!
b1001 #

#40900000000000
0!

#40950000000000
1!
1$
1%

#41000000000000
0!

#41050000000000
1!

#41100000000000
0!

#41150000000000
1!
b100001 #

#41200000000000
0!

#41250000000000
1!

#41300000000000
0!

#41350000000000
1!

#41400000000000
0!

#41450000000000
1!

#41500000000000
0!

#41550000000000
1!

#41600000000000
0!

#41650000000000
1!

#41700000000000
0!

#41750000000000
1!

#41800000000000
0!

#41850000000000
1!

#41900000000000
0!

#41950000000000
1!
b10001 #
0$
0%

#42000000000000
0!

#42050000000000
1!

#42100000000000
0!

#42150000000000
1!

#42200000000000
0!

#42250000000000
1!
b1001 #

#42300000000000
0!

#42350000000000
1!

#42400000000000
0!

#42450000000000
1!

#42500000000000
0!

#42550000000000
1!
b1100 #

#42600000000000
0!

#42650000000000
1!

#42700000000000
0!

#42750000000000
1!

#42800000000000
0!

#42850000000000
1!

#42900000000000
0!

#42950000000000
1!
1$
1%

#43000000000000
0!

#43050000000000
1!

#43100000000000
0!

#43150000000000
1!

#43200000000000
0!

#43250000000000
1!

#43300000000000
0!

#43350000000000
1!
b1010 #

#43400000000000
0!

#43450000000000
1!

#43500000000000
0!

#43550000000000
1!

#43600000000000
0!

#43650000000000
1!
b1001 #

#43700000000000
0!

#43750000000000
1!

#43800000000000
0!

#43850000000000
1!

#43900000000000
0!

#43950000000000
1!
b100001 #
0$
0%

#44000000000000
0!

#44050000000000
1!

#44100000000000
0!

#44150000000000
1!

#44200000000000
0!

#44250000000000
1!

#44300000000000
0!

#44350000000000
1!

#44400000000000
0!

#44450000000000
1!

#44500000000000
0!

#44550000000000
1!

#44600000000000
0!

#44650000000000
1!

#44700000000000
0!

#44750000000000
1!
b10001 #

#44800000000000
0!

#44850000000000
1!

#44900000000000
0!

#44950000000000
1!
1$
1%

#45000000000000
0!

#45050000000000
1!
b1001 #

#45100000000000
0!

#45150000000000
1!

#45200000000000
0!

#45250000000000
1!

#45300000000000
0!

#45350000000000
1!
b1100 #

#45400000000000
0!

#45450000000000
1!

#45500000000000
0!

#45550000000000
1!

#45600000000000
0!

#45650000000000
1!

#45700000000000
0!

#45750000000000
1!

#45800000000000
0!

#45850000000000
1!

#45900000000000
0!

#45950000000000
1!
0$
0%

#46000000000000
0!

#46050000000000
1!

#46100000000000
0!

#46150000000000
1!
b1010 #

#46200000000000
0!

#46250000000000
1!

#46300000000000
0!

#46350000000000
1!

#46400000000000
0!

#46450000000000
1!
b1001 #

#46500000000000
0!

#46550000000000
1!

#46600000000000
0!

#46650000000000
1!

#46700000000000
0!

#46750000000000
1!
b100001 #

#46800000000000
0!

#46850000000000
1!

#46900000000000
0!

#46950000000000
1!
1$
1%

#47000000000000
0!

#47050000000000
1!

#47100000000000
0!

#47150000000000
1!

#47200000000000
0!

#47250000000000
1!

#47300000000000
0!

#47350000000000
1!

#47400000000000
0!

#47450000000000
1!

#47500000000000
0!

#47550000000000
1!
b10001 #

#47600000000000
0!

#47650000000000
1!

#47700000000000
0!

#47750000000000
1!

#47800000000000
0!

#47850000000000
1!
b1001 #

#47900000000000
0!

#47950000000000
1!
0$
0%

#48000000000000
0!

#48050000000000
1!

#48100000000000
0!

#48150000000000
1!
b1100 #

#48200000000000
0!

#48250000000000
1!

#48300000000000
0!

#48350000000000
1!

#48400000000000
0!

#48450000000000
1!

#48500000000000
0!

#48550000000000
1!

#48600000000000
0!

#48650000000000
1!

#48700000000000
0!

#48750000000000
1!

#48800000000000
0!

#48850000000000
1!

#48900000000000
0!

#48950000000000
1!
b1010 #
1$
1%

#49000000000000
0!

#49050000000000
1!

#49100000000000
0!

#49150000000000
1!

#49200000000000
0!

#49250000000000
1!
b1001 #

#49300000000000
0!

#49350000000000
1!

#49400000000000
0!

#49450000000000
1!

#49500000000000
0!

#49550000000000
1!
b100001 #

#49600000000000
0!

#49650000000000
1!

#49700000000000
0!

#49750000000000
1!

#49800000000000
0!

#49850000000000
1!

#49900000000000
0!

#49950000000000
1!
0$
0%

#50000000000000
0!

#50050000000000
1!

#50100000000000
0!

#50150000000000
1!

#50200000000000
0!

#50250000000000
1!

#50300000000000
0!

#50350000000000
1!
b10001 #

#50400000000000
0!

#50450000000000
1!

#50500000000000
0!

#50550000000000
1!

#50600000000000
0!

#50650000000000
1!
b1001 #

#50700000000000
0!

#50750000000000
1!

#50800000000000
0!

#50850000000000
1!

#50900000000000
0!

#50950000000000
1!
b1100 #
1$
1%

#51000000000000
0!

#51050000000000
1!

#51100000000000
0!

#51150000000000
1!

#51200000000000
0!

#51250000000000
1!

#51300000000000
0!

#51350000000000
1!

#51400000000000
0!

#51450000000000
1!

#51500000000000
0!

#51550000000000
1!

#51600000000000
0!

#51650000000000
1!

#51700000000000
0!

#51750000000000
1!
b1010 #

#51800000000000
0!

#51850000000000
1!

#51900000000000
0!

#51950000000000
1!
0$
0%

#52000000000000
0!

#52050000000000
1!
b1001 #

#52100000000000
0!

#52150000000000
1!

#52200000000000
0!

#52250000000000
1!

#52300000000000
0!

#52350000000000
1!
b100001 #

#52400000000000
0!

#52450000000000
1!

#52500000000000
0!

#52550000000000
1!

#52600000000000
0!

#52650000000000
1!

#52700000000000
0!

#52750000000000
1!

#52800000000000
0!

#52850000000000
1!

#52900000000000
0!

#52950000000000
1!
1$
1%

#53000000000000
0!

#53050000000000
1!

#53100000000000
0!

#53150000000000
1!
b10001 #

#53200000000000
0!

#53250000000000
1!

#53300000000000
0!

#53350000000000
1!

#53400000000000
0!

#53450000000000
1!
b1001 #

#53500000000000
0!

#53550000000000
1!

#53600000000000
0!

#53650000000000
1!

#53700000000000
0!

#53750000000000
1!
b1100 #

#53800000000000
0!

#53850000000000
1!

#53900000000000
0!

#53950000000000
1!
0$
0%

#54000000000000
0!

#54050000000000
1!

#54100000000000
0!

#54150000000000
1!

#54200000000000
0!

#54250000000000
1!

#54300000000000
0!

#54350000000000
1!

#54400000000000
0!

#54450000000000
1!

#54500000000000
0!

#54550000000000
1!
b1010 #

#54600000000000
0!

#54650000000000
1!

#54700000000000
0!

#54750000000000
1!

#54800000000000
0!

#54850000000000
1!
b1001 #

#54900000000000
0!

#54950000000000
1!
1$
1%

#55000000000000
0!

#55050000000000
1!

#55100000000000
0!

#55150000000000
1!
b100001 #

#55200000000000
0!

#55250000000000
1!

#55300000000000
0!

#55350000000000
1!

#55400000000000
0!

#55450000000000
1!

#55500000000000
0!

#55550000000000
1!

#55600000000000
0!

#55650000000000
1!

#55700000000000
0!

#55750000000000
1!

#55800000000000
0!

#55850000000000
1!

#55900000000000
0!

#55950000000000
1!
b10001 #
0$
0%

#56000000000000
0!

#56050000000000
1!

#56100000000000
0!

#56150000000000
1!

#56200000000000
0!

#56250000000000
1!
b1001 #

#56300000000000
0!

#56350000000000
1!

#56400000000000
0!

#56450000000000
1!

#56500000000000
0!

#56550000000000
1!
b1100 #

#56600000000000
0!

#56650000000000
1!

#56700000000000
0!

#56750000000000
1!

#56800000000000
0!

#56850000000000
1!

#56900000000000
0!

#56950000000000
1!
1$
1%

#57000000000000
0!

#57050000000000
1!

#57100000000000
0!

#57150000000000
1!

#57200000000000
0!

#57250000000000
1!

#57300000000000
0!

